fsaa/__init__.py
fsaa/attack.py
fsaa/core.py
fsaa/utils.py
fsaa/examples/tutorial.py
fsaa/initializers/__init__.py
fsaa/initializers/random.py
fsaa/initializers/random_sign.py
fsaa/losses/__init__.py
fsaa/losses/cossim_loss.py
fsaa/losses/lpips_loss.py
fsaa/losses/mse_loss.py
fsaa/masks/__init__.py
fsaa/masks/custom.py
fsaa/masks/jnd.py
fsaa/masks/nomask.py
fsaa/models/__init__.py
fsaa/models/cae/__init__.py
fsaa/models/cae/cae.py
fsaa/models/cae/modeling_finetune.py
fsaa/models/cae/utils.py
fsaa/models/hf/hf_models.py
fsaa/models/hub/hub_models.py
fsaa/models/ibot/ibot.py
fsaa/models/ibot/utils.py
fsaa/models/ibot/vits.py
fsaa/models/ijepa/ijepa.py
fsaa/models/ijepa/vision_transformer.py
fsaa/transforms/__init__.py
fsaa/transforms/compose.py
fsaa/transforms/normalize.py
fsaa/updaters/__init__.py
fsaa/updaters/fgsm.py
fsaa/updaters/langevin.py
fsaa/updaters/pgd.py
fsaa/updaters/random.py
fsaa/updaters/lr_schedulers/function.py
fsaa/updaters/lr_schedulers/linear.py
fsaa-0.1.0.dist-info/METADATA
fsaa-0.1.0.dist-info/WHEEL
fsaa-0.1.0.dist-info/licenses/LICENSE
fsaa-0.1.0.dist-info/RECORD
