Metadata-Version: 2.1
Name: fsaa
Version: 0.1.0
Summary: A simple library for adversarial attacks in feature space.
Project-URL: Homepage, https://github.com/BrianPulfer/fsaa
Project-URL: Bug Tracker, https://github.com/BrianPulfer/fsaa/issues
Author-email: Brian Pulfer <brianpulfer95@gmail.com>
License-File: LICENSE
Classifier: License :: Other/Proprietary License
Classifier: Operating System :: OS Independent
Classifier: Programming Language :: Python :: 3
Requires-Python: >=3.8
Requires-Dist: accelerate
Requires-Dist: gdown
Requires-Dist: lpips
Requires-Dist: numpy
Requires-Dist: pre-commit
Requires-Dist: pytest
Requires-Dist: timm
Requires-Dist: torch
Requires-Dist: torchvision
Requires-Dist: tqdm
Requires-Dist: transformers
Requires-Dist: wget
Requires-Dist: xformers
